MoSeka/Activation_util.py
MoSeka/Convolution_util.py
MoSeka/LayerObjects.py
MoSeka/Pooling_util.py
MoSeka/RBF_initial_weight.py
MoSeka/Utils.py
MoSeka/__init__.py
MoSeka/activations.py
MoSeka/evaluation_matrix.py
MoSeka/functional.py
MoSeka/layers.py
MoSeka/losses.py
MoSeka/net.py
MoSeka/utils_func.py
MoSeka-3.0.dist-info/METADATA
MoSeka-3.0.dist-info/WHEEL
MoSeka-3.0.dist-info/license.txt.txt
MoSeka-3.0.dist-info/top_level.txt
MoSeka-3.0.dist-info/RECORD
